dou/__init__.py
dou/__init__.pyi
dou/_logger.py
dou/cli.py
dou_utils-0.1.9.dist-info/licenses/LICENSE
dou_utils-0.1.9.dist-info/METADATA
dou_utils-0.1.9.dist-info/WHEEL
dou_utils-0.1.9.dist-info/entry_points.txt
dou_utils-0.1.9.dist-info/top_level.txt
dou_utils-0.1.9.dist-info/RECORD
