Metadata-Version: 2.4
Name: dou-utils
Version: 0.1.9
Summary: The utility package of Dou Inc.
Requires-Python: >=3.10
License-File: LICENSE
Requires-Dist: loguru>=0.7.3
Requires-Dist: pydantic>=2.11.4
Requires-Dist: toml>=0.10.2
Requires-Dist: typer>=0.15.4
Dynamic: license-file
